knowledgebase_gsheet_gpt.py
knowledgebase_gsheet_gpt-1.2.9.dist-info/METADATA
knowledgebase_gsheet_gpt-1.2.9.dist-info/WHEEL
knowledgebase_gsheet_gpt-1.2.9.dist-info/entry_points.txt
knowledgebase_gsheet_gpt-1.2.9.dist-info/top_level.txt
knowledgebase_gsheet_gpt-1.2.9.dist-info/RECORD
