Metadata-Version: 2.1
Name: knowledgebase-gsheet-gpt
Version: 1.2.9
Summary: UNKNOWN
Home-page: UNKNOWN
License: UNKNOWN
Platform: UNKNOWN
Requires-Dist: google-sheet-downloader (==1.0.7)
Requires-Dist: csv-embeddings-creator (==1.0.7)
Requires-Dist: similarity-ranker (==1.0.3)
Requires-Dist: openai-chat-thread (==1.1.1)
